gemmoai-0.1.51.dist-info/METADATA
gemmoai-0.1.51.dist-info/WHEEL
gemmoai/.gitignore
gemmoai/__init__.py
gemmoai/image/__init__.py
gemmoai/image/image_to_base64.py
gemmoai/pdf/__init__.py
gemmoai/pdf/pdf_to_image.py
gemmoai/prompt/__init__.py
gemmoai/prompt/latest_prompt.py
gemmoai/py.typed
gemmoai/rust.abi3.so
gemmoai-0.1.51.dist-info/RECORD
