Metadata-Version: 2.4
Name: gemmoai
Version: 0.1.51
Requires-Dist: maturin>=1.7.6
Requires-Dist: pillow>=11.1.0
Requires-Dist: pymupdf>=1.24.14
Requires-Dist: tomli>=2.2.1
Summary: GemmoAI Python Library
Author-email: Giacomo Piccinini <giacomo.piccinini@gemmo.ai>, Elisa Castelli <elisa.castelli@gemmo.ai>, Nicolò Pisanu <nicolo.pisanu@gemmo.ai>
Requires-Python: >=3.10
